netdata_pandas/__init__.py
netdata_pandas/_nbdev.py
netdata_pandas/data.py
netdata_pandas/data_cloud.py
netdata_pandas/utils.py
netdata_pandas/wrangle.py
netdata_pandas-0.0.46.dist-info/LICENSE
netdata_pandas-0.0.46.dist-info/METADATA
netdata_pandas-0.0.46.dist-info/WHEEL
netdata_pandas-0.0.46.dist-info/top_level.txt
netdata_pandas-0.0.46.dist-info/RECORD
